LICENSE
README.md
setup.py
bin/darepyperun.py
darepype/__init__.py
darepype.egg-info/PKG-INFO
darepype.egg-info/SOURCES.txt
darepype.egg-info/dependency_links.txt
darepype.egg-info/requires.txt
darepype.egg-info/top_level.txt
darepype/drp/__init__.py
darepype/drp/datafits.py
darepype/drp/dataparent.py
darepype/drp/datatext.py
darepype/drp/pipeline.py
darepype/drp/stepmiparent.py
darepype/drp/stepmoparent.py
darepype/drp/stepniparent.py
darepype/drp/stepparent.py
darepype/tools/__init__.py
darepype/tools/steploadaux.py
darepype/tools/steplogsocket.py
darepype/tools/steptemplate.py
darepype/utils/__init__.py
darepype/utils/stepdatagroup.py
darepype/utils/stepsubpipe.py
tests/test_bin.py
tests/test_objects.py
tests/test_piping.py