Metadata-Version: 2.1
Name: darepype
Version: 0.1.7
Summary: DAta REduction PYPEline framework
Home-page: https://github.com/berthoud/darepype
Author: HAWC Team
Author-email: marcberthoud@uchicago.edu
License: GNU GPL v3+
Classifier: Programming Language :: Python :: 3
Classifier: Programming Language :: Python :: 3.6
Classifier: Programming Language :: Python :: 3.8
Classifier: Programming Language :: Python :: 3.9
License-File: LICENSE
Requires-Dist: configobj
